{
  "posts": [
    {
      "id": "launch",
      "text": "Dust Protocol — Genesis mint is live on Monad.\nMinted: {{MINTED}}/{{MAX_SUPPLY}}\nPrice: 33 MON • Supply: 3333 • 7-day window\n\n{{FEE_BANNER}}\n\nMint: {{MINT_URL}}\nContract: {{NFT_CONTRACT}}"
    },
    {
      "id": "progress",
      "text": "Live mint counter + countdown are on the mint page.\n{{COUNTDOWN}}\nAnything unminted at the end of the window is burned by contract logic.\n\n{{FEE_BANNER}}\n\nMint: {{MINT_URL}}\nContract: {{NFT_CONTRACT}}"
    },
    {
      "id": "stage2",
      "text": "Next milestone: Stage 2 public dust cleaning.\nUsers clean dust → protocol fee → 33% shared monthly to NFT holders.\n\n{{FEE_BANNER}}\n\nMint: {{MINT_URL}}\nContract: {{NFT_CONTRACT}}"
    }
  ],
  "replies": [
    {
      "match": ["why", "utility", "benefit", "worth"],
      "text": "{{FEE_BANNER}}\nStage 2: public dust cleaning (users pay a fee). Plan: monthly distributions to holders.\nMint page (live counter + countdown): {{MINT_URL}}"
    },
    {
      "match": ["where", "link", "mint", "how", "minting"],
      "text": "Mint is live: {{MINT_URL}}\nPrice: 33 MON\n{{COUNTDOWN}}\nContract: {{NFT_CONTRACT}}\n{{FEE_BANNER}}"
    },
    {
      "match": ["trust", "scam", "safe", "verified"],
      "text": "Everything is on-chain + public. Contract: {{NFT_CONTRACT}}\nMint page shows live counter + countdown: {{MINT_URL}}"
    },
    {
      "match": ["stage 2", "fees", "rebate", "revenue", "share", "holders"],
      "text": "{{FEE_BANNER}}\nStage 2 enables public dust cleaning with protocol fees.\nMint: {{MINT_URL}}"
    },
    {
      "match": ["burn", "burned", "unsold", "deadline", "7 days", "mint ends"],
      "text": "Mint window is 7 days. After it ends, remaining unminted supply is burned by contract logic.\n{{COUNTDOWN}}\nMint: {{MINT_URL}}"
    },
    {
      "match": ["price", "cost"],
      "text": "Mint price is 33 MON per NFT.\nMint: {{MINT_URL}}\n{{COUNTDOWN}}"
    }
  ]
}

